ml_explain_preprocess/__init__.py
ml_explain_preprocess/preprocess.py
ml_explain_preprocess/reports.py
ml_explain_preprocess-0.1.1.dist-info/licenses/LICENSE
ml_explain_preprocess-0.1.1.dist-info/METADATA
ml_explain_preprocess-0.1.1.dist-info/WHEEL
ml_explain_preprocess-0.1.1.dist-info/top_level.txt
ml_explain_preprocess-0.1.1.dist-info/RECORD
