Metadata-Version: 2.4
Name: ml-explain-preprocess
Version: 0.1.1
Summary: Explainable preprocessing for ML pipelines with reports and visualizations.
Author-email: Rishee Panchal <backpropnomad@gmail.com>
License-Expression: MIT
Project-URL: Repository, https://github.com/risheeee/ml-explain-preprocess.git
Classifier: Programming Language :: Python :: 3
Classifier: Operating System :: OS Independent
Classifier: Topic :: Scientific/Engineering :: Artificial Intelligence
Requires-Python: >=3.8
License-File: LICENSE
Requires-Dist: pandas>=1.5.0
Requires-Dist: numpy>=1.23.0
Requires-Dist: scikit-learn>=1.2.0
Requires-Dist: matplotlib>=3.6.0
Requires-Dist: seaborn>=0.12.0
Dynamic: license-file
